Metadata-Version: 1.0
Name: loocius
Version: 0.1
Summary: A skeleton for creating psychological tests in Python
Home-page: http://github.com/sammosummo/loocius
Author: Sam Mathias
Author-email: samuel.mathias@gmail.com
License: MIT
Platform: UNKNOWN
